genuine_bs/__init__.py
genuine_bs/bs.py
genuine_bs/vocab.py
genuine_bs_shengxio-1.2.3.dist-info/LICENSE
genuine_bs_shengxio-1.2.3.dist-info/METADATA
genuine_bs_shengxio-1.2.3.dist-info/WHEEL
genuine_bs_shengxio-1.2.3.dist-info/top_level.txt
genuine_bs_shengxio-1.2.3.dist-info/RECORD
