Metadata-Version: 2.1
Name: genuine-bs-shengxio
Version: 1.2.3
Summary: A complete random content generator created based on en_core_web_md vocabulary.
Home-page: https://github.com/shengxio/genuine_bs
Author: Roland Ding
Author-email: shengxio@ualberta.ca
License: UNKNOWN
Project-URL: Bug Tracker, https://github.com/shengxio/genuine_bs/issues
Platform: UNKNOWN
Classifier: Programming Language :: Python :: 3
Classifier: License :: OSI Approved :: MIT License
Classifier: Operating System :: OS Independent
Requires-Python: >=3.6
License-File: LICENSE
